LICENSE
MANIFEST.in
README.rst
setup.py
pwho/__init__.py
pwho/exc.py
pwho.egg-info/PKG-INFO
pwho.egg-info/SOURCES.txt
pwho.egg-info/dependency_links.txt
pwho.egg-info/requires.txt
pwho.egg-info/top_level.txt