Metadata-Version: 1.1
Name: pwho
Version: 0.1.0
Summary: PROXY protcol: http://www.haproxy.org/download/1.5/doc/proxy-protocol.txt.
Home-page: https://github.com/bninja/pwho
Author: Etal
Author-email: et@al.org
License: BSD
Platform: any
Classifier: Intended Audience :: Developers
Classifier: License :: OSI Approved :: BSD License
Classifier: Operating System :: OS Independent
Classifier: Programming Language :: Python
Classifier: Topic :: Internet :: WWW/HTTP :: Dynamic Content
Classifier: Topic :: Software Development :: Libraries :: Python Modules
